MANIFEST.in
README.md
setup.py
llm_req/__init__.py
llm_req/cmd.py
llm_req/embeding.py
llm_req/llm.py
llm_req/normal.py
llm_req/struct.py
llm_req/tool.py
llm_req/voice.py
llm_req.egg-info/PKG-INFO
llm_req.egg-info/SOURCES.txt
llm_req.egg-info/dependency_links.txt
llm_req.egg-info/entry_points.txt
llm_req.egg-info/not-zip-safe
llm_req.egg-info/requires.txt
llm_req.egg-info/top_level.txt
llm_req/agent/__init__.py
llm_req/agent/base.py